i3_cycle.py
i3_cycle-1.0.dist-info/DESCRIPTION.rst
i3_cycle-1.0.dist-info/METADATA
i3_cycle-1.0.dist-info/RECORD
i3_cycle-1.0.dist-info/WHEEL
i3_cycle-1.0.dist-info/entry_points.txt
i3_cycle-1.0.dist-info/metadata.json
i3_cycle-1.0.dist-info/top_level.txt
