Metadata-Version: 2.0
Name: i3-cycle
Version: 1.0
Summary: Cycle focus through i3 containers
Home-page: http://github.com/mota/i3-cycle
Author: Pierre Wacrenier
Author-email: mota@souitom.org
License: ISC
Platform: UNKNOWN
Requires-Dist: i3-tree
